primoslist/__init__.py
primoslist-1.3.dist-info/LICENSE
primoslist-1.3.dist-info/METADATA
primoslist-1.3.dist-info/WHEEL
primoslist-1.3.dist-info/top_level.txt
primoslist-1.3.dist-info/RECORD
