Metadata-Version: 2.1
Name: primoslist
Version: 1.3
Summary: Simple tool to perform mathematical operations.
Home-page: UNKNOWN
Author: Ppi
Author-email: UNKNOWN
License: GNU GPLv3
Keywords: pyoperaciones mathematical operations
Platform: UNKNOWN
Classifier: Development Status :: 3 - Alpha
Classifier: Intended Audience :: Developers
Classifier: Topic :: Utilities
Classifier: License :: OSI Approved :: GNU General Public License v3 (GPLv3)
Classifier: Programming Language :: Python :: 3
Classifier: Operating System :: OS Independent
